monotonescheme.cpython-36m-darwin.so
monotonescheme-0.0.19.dist-info/LICENSE
monotonescheme-0.0.19.dist-info/METADATA
monotonescheme-0.0.19.dist-info/WHEEL
monotonescheme-0.0.19.dist-info/top_level.txt
monotonescheme-0.0.19.dist-info/RECORD
