Metadata-Version: 2.1
Name: monotonescheme
Version: 0.0.19
Summary: Python wrapper for C++ codes for the monotone scheme for curvature-driven PDEs
Home-page: https://github.com/wonjunee/monotone-scheme
Author: Wonjun Lee
Author-email: wlee@ucla.edu
License: UNKNOWN
Platform: UNKNOWN
Classifier: Programming Language :: Python :: 3
Classifier: License :: OSI Approved :: MIT License
Classifier: Operating System :: OS Independent
Requires-Python: >=3.6
Requires-Dist: numpy
Requires-Dist: scipy
Requires-Dist: scikit-learn
Requires-Dist: matplotlib
Requires-Dist: tqdm
Requires-Dist: plotly
Requires-Dist: ipython
Requires-Dist: ipykernel
Requires-Dist: nbformat (>=5)
Requires-Dist: graphlearning
